combu/__init__.py
combu/_combu.py
combu/definition.py
combu/execution.py
combu/generator.py
combu/parallel.py
combu/util.py
combu-1.2.1.dist-info/LICENSE
combu-1.2.1.dist-info/WHEEL
combu-1.2.1.dist-info/METADATA
combu-1.2.1.dist-info/RECORD
