Metadata-Version: 2.1
Name: combu
Version: 1.2.1
Summary: Execute your method with combination parameters.
Home-page: https://github.com/takelushi/combu
License: MIT
Author: Takeru Saito
Author-email: takelushi@gmail.com
Requires-Python: >=3.6,<4.0
Classifier: License :: OSI Approved :: MIT License
Classifier: Programming Language :: Python :: 3
Classifier: Programming Language :: Python :: 3.6
Classifier: Programming Language :: Python :: 3.7
Classifier: Programming Language :: Python :: 3.8
Classifier: Programming Language :: Python :: 3.9
Requires-Dist: tqdm (>=4.56.0,<5.0.0)
Project-URL: Repository, https://github.com/takelushi/combu
Project-URL: issues, https://github.com/takelushi/combu/issues
